MANIFEST.in
README.md
setup.py
church_encoding/__init__.py
church_encoding/church.py
church_encoding.egg-info/PKG-INFO
church_encoding.egg-info/SOURCES.txt
church_encoding.egg-info/dependency_links.txt
church_encoding.egg-info/top_level.txt
church_encoding/test/__init__.py
church_encoding/test/church_test.py